LICENSE
README.md
setup.cfg
setup.py
fs_attestation_safe_cli.egg-info/PKG-INFO
fs_attestation_safe_cli.egg-info/SOURCES.txt
fs_attestation_safe_cli.egg-info/dependency_links.txt
fs_attestation_safe_cli.egg-info/entry_points.txt
fs_attestation_safe_cli.egg-info/requires.txt
fs_attestation_safe_cli.egg-info/top_level.txt
safe_cli/__init__.py
safe_cli/argparse_validators.py
safe_cli/ethereum_hd_wallet.py
safe_cli/main.py
safe_cli/prompt_parser.py
safe_cli/safe_addresses.py
safe_cli/safe_completer.py
safe_cli/safe_completer_constants.py
safe_cli/safe_creator.py
safe_cli/safe_lexer.py
safe_cli/utils.py
safe_cli/version.py
safe_cli/contracts/__init__.py
safe_cli/contracts/safe_to_l2_migration.py
safe_cli/operators/__init__.py
safe_cli/operators/enums.py
safe_cli/operators/exceptions.py
safe_cli/operators/fs_attestation_auth.py
safe_cli/operators/fs_attestation_service_operator.py
safe_cli/operators/safe_operator.py
safe_cli/operators/safe_tx_service_operator.py
safe_cli/operators/hw_wallets/__init__.py
safe_cli/operators/hw_wallets/constants.py
safe_cli/operators/hw_wallets/exceptions.py
safe_cli/operators/hw_wallets/hw_wallet.py
safe_cli/operators/hw_wallets/hw_wallet_manager.py
safe_cli/operators/hw_wallets/ledger_exceptions.py
safe_cli/operators/hw_wallets/ledger_wallet.py
safe_cli/operators/hw_wallets/trezor_exceptions.py
safe_cli/operators/hw_wallets/trezor_wallet.py
tests/__init__.py
tests/safe_cli_test_case_mixin.py
tests/test_argparse_validators.py
tests/test_entrypoint.py
tests/test_ethereum_hd_wallet.py
tests/test_hw_wallet_manager.py
tests/test_ledger_wallet.py
tests/test_safe_addresses.py
tests/test_safe_cli.py
tests/test_safe_completer.py
tests/test_safe_creator.py
tests/test_safe_lexer.py
tests/test_safe_operator.py
tests/test_safe_tx_service_operator.py
tests/test_trezor_wallet.py
tests/test_utils.py
tests/utils.py
tests/mocks/__init__.py
tests/mocks/balances_mock.py
tests/mocks/data_decoded_mock.py
tests/mocks/multisig_tx_mock.py
tests/mocks/txs_mock.py