Metadata-Version: 2.1
Name: fs-attestation-safe-cli
Version: 1.0.8
Summary: Modified Command Line Interface for FailSafe Attestation Service to administrate Gnosis Safe Wallets and FailSafe Attestation Guard Contracts
Home-page: https://github.com/gnosis/safe-cli
Download-URL: https://github.com/gnosis/safe-cli/releases
Author: Mohan
Author-email: mohan@ethlas.com
License: MIT
Classifier: Programming Language :: Python
Classifier: Programming Language :: Python :: 3.9
Classifier: Programming Language :: Python :: 3.10
Classifier: Programming Language :: Python :: 3.11
Classifier: Programming Language :: Python :: 3.12
Classifier: License :: OSI Approved :: MIT License
Classifier: Operating System :: OS Independent
Requires-Python: >=3.9
Provides-Extra: ledger
Provides-Extra: trezor
License-File: LICENSE
